bnum/__init__.py
bnum/_version.py
bnum/py.typed
bnum-0.3.dist-info/METADATA
bnum-0.3.dist-info/WHEEL
bnum-0.3.dist-info/licenses/LICENSE.rst
bnum-0.3.dist-info/RECORD
