Metadata-Version: 2.4
Name: bnum
Version: 0.3
Summary: Bounded numbers
Project-URL: Homepage, https://github.com/eykd/bnum
Project-URL: Issues, https://github.com/eykd/bnum/issues
Project-URL: Repository, https://github.com/eykd/bnum
Author-email: David Eyk <david@worldsenoughstudios.com>
License-Expression: MIT
License-File: LICENSE.rst
Classifier: Development Status :: 4 - Beta
Classifier: Environment :: Console
Classifier: Intended Audience :: Developers
Classifier: Intended Audience :: Information Technology
Classifier: License :: OSI Approved :: MIT License
Classifier: Operating System :: OS Independent
Classifier: Programming Language :: Python
Requires-Python: >=3.11
